hc05config/AT_command.py
hc05config/__init__.py
hc05config/__main__.py
hc05config/basic_info.py
hc05config/bluetooth_config.py
hc05config/input_lib.py
hc05config/master_and_slave.py
hc05config/port_select.py
hc05config/preset.py
HC_05_ConfigTool-0.1.1.dist-info/LICENSE
HC_05_ConfigTool-0.1.1.dist-info/METADATA
HC_05_ConfigTool-0.1.1.dist-info/WHEEL
HC_05_ConfigTool-0.1.1.dist-info/top_level.txt
HC_05_ConfigTool-0.1.1.dist-info/RECORD
