Metadata-Version: 2.1
Name: HC-05-ConfigTool
Version: 0.1.1
Summary: A terminal tool for configuring HC-05 with AT mode.
Home-page: https://github.com/Doma1204/HC-05_Bluetooth_Tool
Author: Joseph Lam
Author-email: mhlamaf@connect.ust.hk
License: MIT
Keywords: bluetooth hc-05
Platform: UNKNOWN
Classifier: Development Status :: 5 - Production/Stable
Classifier: Topic :: Utilities
Classifier: Natural Language :: English
Classifier: License :: OSI Approved :: MIT License
Classifier: Programming Language :: Python :: 3
Classifier: Programming Language :: Python :: 3.2
Classifier: Programming Language :: Python :: 3.3
Classifier: Programming Language :: Python :: 3.4
Classifier: Programming Language :: Python :: 3.5
Classifier: Programming Language :: Python :: 3.6
Classifier: Programming Language :: Python :: 3.7
Requires-Python: >=3
Requires-Dist: pyserial
